escpy/__init__.py
escpy/crystal.py
escpy/elasticity.py
escpy-0.2.3.dist-info/METADATA
escpy-0.2.3.dist-info/RECORD
escpy-0.2.3.dist-info/WHEEL
escpy-0.2.3.dist-info/top_level.txt
