Metadata-Version: 2.1
Name: escpy
Version: 0.2.3
Summary: A package that implements Born stability conditions
Home-page: https://github.com/MineralsCloud/elastic-stability-conditions
Author: Qi Zhang
Author-email: qz2280@columbia.edu
Maintainer: Qi Zhang
Maintainer-email: qz2280@columbia.edu
License: MIT
Platform: UNKNOWN
Classifier: Development Status :: 5 - Production/Stable
Classifier: Intended Audience :: Science/Research
Classifier: Topic :: Scientific/Engineering :: Physics
Classifier: License :: OSI Approved :: GNU General Public License v3 (GPLv3)
Classifier: Programming Language :: Python :: 3.5
Classifier: Programming Language :: Python :: 3.6
Requires-Python: >=3.5
Requires-Dist: numpy
